wagtailterms/__init__.py
wagtailterms/apps.py
wagtailterms/default_settings.py
wagtailterms/models.py
wagtailterms/permissions.py
wagtailterms/serializers.py
wagtailterms/testing.py
wagtailterms/tests.py
wagtailterms/urls.py
wagtailterms/views.py
wagtailterms/wagtail_hooks.py
wagtailterms/migrations/0001_initial.py
wagtailterms/migrations/0002_wagtailtermtag_term_tags.py
wagtailterms/migrations/__init__.py
wagtailterms/static/wagtailterms/popperjs.js
wagtailterms/static/wagtailterms/term.js
wagtailterms/static/wagtailterms/tippyjs.js
wagtailterms/templates/wagtailterms/wagtailterms.html
wagtailterms-0.2.1.dist-info/licenses/LICENSE
wagtailterms-0.2.1.dist-info/METADATA
wagtailterms-0.2.1.dist-info/WHEEL
wagtailterms-0.2.1.dist-info/top_level.txt
wagtailterms-0.2.1.dist-info/RECORD
